odoo10_addon_business_requirement_deliverable_crm-10.0.1.0.0-py2.7-nspkg.pth
odoo/addons/business_requirement_deliverable_crm/README.rst
odoo/addons/business_requirement_deliverable_crm/__init__.py
odoo/addons/business_requirement_deliverable_crm/__manifest__.py
odoo/addons/business_requirement_deliverable_crm/data/business_requirement_deliverable_crm_demo.xml
odoo/addons/business_requirement_deliverable_crm/i18n/sl.po
odoo/addons/business_requirement_deliverable_crm/models/__init__.py
odoo/addons/business_requirement_deliverable_crm/models/crm.py
odoo/addons/business_requirement_deliverable_crm/static/description/icon.png
odoo/addons/business_requirement_deliverable_crm/tests/__init__.py
odoo/addons/business_requirement_deliverable_crm/tests/test_br.py
odoo/addons/business_requirement_deliverable_crm/tests/test_wizard_br.py
odoo/addons/business_requirement_deliverable_crm/views/crm_view.xml
odoo/addons/business_requirement_deliverable_crm/wizard/__init__.py
odoo/addons/business_requirement_deliverable_crm/wizard/crm_make_sale.py
odoo/addons/business_requirement_deliverable_crm/wizard/crm_make_sale_view.xml
odoo10_addon_business_requirement_deliverable_crm-10.0.1.0.0.dist-info/DESCRIPTION.rst
odoo10_addon_business_requirement_deliverable_crm-10.0.1.0.0.dist-info/METADATA
odoo10_addon_business_requirement_deliverable_crm-10.0.1.0.0.dist-info/RECORD
odoo10_addon_business_requirement_deliverable_crm-10.0.1.0.0.dist-info/WHEEL
odoo10_addon_business_requirement_deliverable_crm-10.0.1.0.0.dist-info/metadata.json
odoo10_addon_business_requirement_deliverable_crm-10.0.1.0.0.dist-info/namespace_packages.txt
odoo10_addon_business_requirement_deliverable_crm-10.0.1.0.0.dist-info/top_level.txt
